setup.py
src/radical/__init__.py
src/radical.ensemblemd.ensembleapi.egg-info/PKG-INFO
src/radical.ensemblemd.ensembleapi.egg-info/SOURCES.txt
src/radical.ensemblemd.ensembleapi.egg-info/dependency_links.txt
src/radical.ensemblemd.ensembleapi.egg-info/entry_points.txt
src/radical.ensemblemd.ensembleapi.egg-info/namespace_packages.txt
src/radical.ensemblemd.ensembleapi.egg-info/not-zip-safe
src/radical.ensemblemd.ensembleapi.egg-info/requires.txt
src/radical.ensemblemd.ensembleapi.egg-info/top_level.txt
src/radical/ensemblemd/__init__.py
src/radical/ensemblemd/ensembleapi/VERSION
src/radical/ensemblemd/ensembleapi/__init__.py
src/radical/ensemblemd/ensembleapi/bin/__init__.py
src/radical/ensemblemd/ensembleapi/bin/linker.py
src/radical/ensemblemd/ensembleapi/bin/mdAPI.py
src/radical/ensemblemd/ensembleapi/bin/runme.py