Metadata-Version: 1.1
Name: radical.ensemblemd.ensembleapi
Version: 0.1
Summary:  A library to run bulk gromacs tasks on DCI.
Home-page: https://github.com/radical-cybertools
Author: Vivek Balasubramanian
Author-email: vivek.balasubramanian@rutgers.edu
License: MIT
Keywords: molecular dynamics workflow
Platform: UNKNOWN
Classifier: Development Status :: 5 - Production/Stable
Classifier: Intended Audience :: Developers
Classifier: Environment :: Console
Classifier: Programming Language :: Python
Classifier: Programming Language :: Python :: 2
Classifier: Programming Language :: Python :: 2.5
Classifier: Programming Language :: Python :: 2.6
Classifier: Programming Language :: Python :: 2.7
Classifier: Topic :: Utilities
Classifier: Topic :: System :: Distributed Computing
Classifier: Operating System :: MacOS :: MacOS X
Classifier: Operating System :: POSIX
Classifier: Operating System :: Unix
